checkov/__init__.py
checkov/logging_init.py
checkov/main.py
checkov/py.typed
checkov/runner_filter.py
checkov/version.py
checkov/argo_workflows/__init__.py
checkov/argo_workflows/runner.py
checkov/argo_workflows/checks/__init__.py
checkov/argo_workflows/checks/base_argo_workflows_check.py
checkov/argo_workflows/checks/registry.py
checkov/argo_workflows/checks/template/DefaultServiceAccount.py
checkov/argo_workflows/checks/template/RunAsNonRoot.py
checkov/argo_workflows/checks/template/__init__.py
checkov/argo_workflows/common/__init__.py
checkov/arm/__init__.py
checkov/arm/base_parameter_check.py
checkov/arm/base_registry.py
checkov/arm/base_resource_check.py
checkov/arm/base_resource_value_check.py
checkov/arm/context_parser.py
checkov/arm/registry.py
checkov/arm/runner.py
checkov/arm/checks/__init__.py
checkov/arm/checks/parameter/SecureStringParameterNoHardcodedValue.py
checkov/arm/checks/parameter/__init__.py
checkov/arm/checks/resource/AKSApiServerAuthorizedIpRanges.py
checkov/arm/checks/resource/AKSDashboardDisabled.py
checkov/arm/checks/resource/AKSLoggingEnabled.py
checkov/arm/checks/resource/AKSNetworkPolicy.py
checkov/arm/checks/resource/AKSRbacEnabled.py
checkov/arm/checks/resource/AppServiceAuthentication.py
checkov/arm/checks/resource/AppServiceClientCertificate.py
checkov/arm/checks/resource/AppServiceHTTPSOnly.py
checkov/arm/checks/resource/AppServiceHttps20Enabled.py
checkov/arm/checks/resource/AppServiceIdentity.py
checkov/arm/checks/resource/AppServiceMinTLSVersion.py
checkov/arm/checks/resource/AzureInstancePassword.py
checkov/arm/checks/resource/AzureManagedDiscEncryption.py
checkov/arm/checks/resource/AzureScaleSetPassword.py
checkov/arm/checks/resource/CosmosDBDisableAccessKeyWrite.py
checkov/arm/checks/resource/CustomRoleDefinitionSubscriptionOwner.py
checkov/arm/checks/resource/KeyvaultRecoveryEnabled.py
checkov/arm/checks/resource/MariaDBSSLEnforcementEnabled.py
checkov/arm/checks/resource/MonitorLogProfileCategories.py
checkov-2.1.284.dist-info/LICENSE
checkov-2.1.284.dist-info/METADATA
checkov-2.1.284.dist-info/WHEEL
checkov-2.1.284.dist-info/top_level.txt
checkov-2.1.284.dist-info/RECORD
