Metadata-Version: 2.1
Name: checkov
Version: 2.1.284
Summary: Infrastructure as code static analysis
Home-page: https://github.com/bridgecrewio/checkov
Author: bridgecrew
Author-email: meet@bridgecrew.io
License: Apache License 2.0
Classifier: Environment :: Console
Classifier: Intended Audience :: Developers
Classifier: Intended Audience :: System Administrators
Classifier: License :: OSI Approved :: Apache Software License
Classifier: Programming Language :: Python :: 3 :: Only
Classifier: Programming Language :: Python :: 3.7
Classifier: Programming Language :: Python :: 3.8
Classifier: Programming Language :: Python :: 3.9
Classifier: Programming Language :: Python :: 3.10
Classifier: Programming Language :: Python :: 3.11
Classifier: Topic :: Security
Classifier: Topic :: Software Development :: Build Tools
Classifier: Typing :: Typed
Requires-Python: >=3.7
License-File: LICENSE
Requires-Dist: bc-python-hcl2 (==0.3.47)
Requires-Dist: bc-detect-secrets (==1.3.9)
Requires-Dist: deep-merge
Requires-Dist: tabulate
Requires-Dist: colorama
Requires-Dist: termcolor
Requires-Dist: junit-xml (>=1.9)
Requires-Dist: dpath (<2,>=1.5.0)
Requires-Dist: pyyaml (>=5.4.1)
Requires-Dist: boto3 (>=1.17)
Requires-Dist: gitpython
Requires-Dist: jmespath
Requires-Dist: tqdm
Requires-Dist: update-checker
Requires-Dist: semantic-version
Requires-Dist: packaging
Requires-Dist: cloudsplaining (>=0.4.3)
Requires-Dist: networkx (<2.7)
Requires-Dist: dockerfile-parse
Requires-Dist: docker
Requires-Dist: configargparse
Requires-Dist: argcomplete
Requires-Dist: policyuniverse
Requires-Dist: typing-extensions (>=4.1.0)
Requires-Dist: importlib-metadata (>=0.12)
Requires-Dist: cachetools
Requires-Dist: cyclonedx-python-lib (<4.0.0,>=2.4.0)
Requires-Dist: packageurl-python
Requires-Dist: click (>=8.0.0)
Requires-Dist: aiohttp
Requires-Dist: aiodns
Requires-Dist: aiomultiprocess
Requires-Dist: jsonpath-ng
Requires-Dist: jsonschema (<4.0.0,>=3.0.2)
Requires-Dist: prettytable (>=3.0.0)
Requires-Dist: pycep-parser (==0.3.9)
Requires-Dist: charset-normalizer
Requires-Dist: schema
Requires-Dist: pyston-autoload (==2.3.5) ; python_version < "3.11" and (sys_platform == "linux" or sys_platform == "darwin") and platform_machine == "x86_64"
Requires-Dist: pyston (==2.3.5) ; python_version < "3.11" and (sys_platform == "linux" or sys_platform == "darwin") and platform_machine == "x86_64"
Provides-Extra: dev
Requires-Dist: pytest (==5.3.1) ; extra == 'dev'
Requires-Dist: coverage (==5.5) ; extra == 'dev'
Requires-Dist: coverage-badge ; extra == 'dev'
Requires-Dist: GitPython (==3.1.7) ; extra == 'dev'
Requires-Dist: bandit ; extra == 'dev'
Requires-Dist: jsonschema ; extra == 'dev'
